poofapi/__init__.py
poofapi/api.py
poofapi/models.py
poofapi-1.0.2.dist-info/LICENSE
poofapi-1.0.2.dist-info/METADATA
poofapi-1.0.2.dist-info/WHEEL
poofapi-1.0.2.dist-info/top_level.txt
poofapi-1.0.2.dist-info/RECORD
